dexstore/__init__.py
dexstore/account.py
dexstore/amount.py
dexstore/asset.py
dexstore/block.py
dexstore/blockchain.py
dexstore/blockchainobject.py
dexstore/committee.py
dexstore/dex.py
dexstore/dexstore.py
dexstore/exceptions.py
dexstore/htlc.py
dexstore/instance.py
dexstore/market.py
dexstore/memo.py
dexstore/message.py
dexstore/notify.py
dexstore/price.py
dexstore/proposal.py
dexstore/storage.py
dexstore/transactionbuilder.py
dexstore/utils.py
dexstore/vesting.py
dexstore/wallet.py
dexstore/witness.py
dexstore/worker.py
dexstoreapi/__init__.py
dexstoreapi/dexstorenoderpc.py
dexstoreapi/exceptions.py
dexstoreapi/websocket.py
dexstorebase/__init__.py
dexstorebase/account.py
dexstorebase/asset_permissions.py
dexstorebase/bip38.py
dexstorebase/chains.py
dexstorebase/memo.py
dexstorebase/objects.py
dexstorebase/objecttypes.py
dexstorebase/operationids.py
dexstorebase/operations.py
dexstorebase/signedtransactions.py
dexstorebase/transactions.py
dexstore-1.2.4.dist-info/AUTHORS
dexstore-1.2.4.dist-info/LICENSE.txt
dexstore-1.2.4.dist-info/METADATA
dexstore-1.2.4.dist-info/WHEEL
dexstore-1.2.4.dist-info/top_level.txt
dexstore-1.2.4.dist-info/RECORD
