Metadata-Version: 2.1
Name: dexstore
Version: 1.2.4
Summary: Python library for dexstore
Home-page: https://github.com/rolik2001/python-dexstore
Author: Fabian Schuh
Author-email: Fabian@chainsquad.com
Maintainer: Fabian Schuh
Maintainer-email: Fabian@chainsquad.com
License: UNKNOWN
Download-URL: https://github.com/rolik2001/python-dexstore/tarball/1.2.4
Keywords: dexstore,library,api,rpc
Platform: UNKNOWN
Classifier: License :: OSI Approved :: MIT License
Classifier: Operating System :: OS Independent
Classifier: Programming Language :: Python :: 3
Classifier: Development Status :: 3 - Alpha
Classifier: Intended Audience :: Developers
Classifier: Intended Audience :: Financial and Insurance Industry
Classifier: Topic :: Office/Business :: Financial
Requires-Dist: graphenelib (>=1.1.11)
Requires-Dist: pycryptodome
Requires-Dist: websockets
Requires-Dist: appdirs
Requires-Dist: Events
Requires-Dist: scrypt
Requires-Dist: pyyaml
